MANIFEST.in
README.md
setup.py
neurobytes/__init__.py
neurobytes/autoflash.py
neurobytes/cli.py
neurobytes/edit_elf.py
neurobytes/exceptions.py
neurobytes/gdbProcess.py
neurobytes.egg-info/PKG-INFO
neurobytes.egg-info/SOURCES.txt
neurobytes.egg-info/dependency_links.txt
neurobytes.egg-info/entry_points.txt
neurobytes.egg-info/not-zip-safe
neurobytes.egg-info/requires.txt
neurobytes.egg-info/top_level.txt
neurobytes/firmware/__init__.py
neurobytes/firmware/firmware.py
neurobytes/interfaces/__init__.py
neurobytes/interfaces/blackmagic.py
neurobytes/interfaces/interface.py