Metadata-Version: 1.0
Name: neurobytes
Version: 0.16
Summary: NeuroBytes Python Module and CLI
Home-page: https://github.com/NeuroTinker/neurobytes-python
Author: Jarod White
Author-email: jrwhite20@gmail.com
License: GNU
Platform: UNKNOWN
